<?xml version="1.0" encoding="UTF-8"?><?xml-stylesheet type='text/xsl' href='_UpgradeReport_Files/UpgradeReport.xslt'?><UpgradeLog>
<Properties><Property Name="Solution" Value="Unity">
</Property><Property Name="Solution File" Value="C:\Repository\Sandbox\Msdn\UnitySource\UnitySource\Unity.sln">
</Property><Property Name="Date" Value="21 April 2010">
</Property><Property Name="Time" Value="20:01">
</Property></Properties><Event ErrorLevel="1" Project="ObjectBuilder" Source="Src\ObjectBuilder\ObjectBuilder.csproj" Description="Your project is targeting .NET Framework 2.0 or 3.0. If your project uses assemblies requiring a newer .NET Framework, your project will fail to build. You can change the .NET Framework version by clicking Properties on the project menu and then selecting a new version in the '.NET Framework' dropdown box. (In Visual Basic, this is located on the Compile tab by clicking the 'Advanced Compiler Options...' button.)">
</Event><Event ErrorLevel="0" Project="ObjectBuilder" Source="Src\ObjectBuilder\ObjectBuilder.csproj" Description="Project converted successfully">
</Event><Event ErrorLevel="3" Project="ObjectBuilder" Source="Src\ObjectBuilder\ObjectBuilder.csproj" Description="Converted">
</Event><Event ErrorLevel="1" Project="Unity" Source="Src\Unity\Unity.csproj" Description="Your project is targeting .NET Framework 2.0 or 3.0. If your project uses assemblies requiring a newer .NET Framework, your project will fail to build. You can change the .NET Framework version by clicking Properties on the project menu and then selecting a new version in the '.NET Framework' dropdown box. (In Visual Basic, this is located on the Compile tab by clicking the 'Advanced Compiler Options...' button.)">
</Event><Event ErrorLevel="0" Project="Unity" Source="Src\Unity\Unity.csproj" Description="Project converted successfully">
</Event><Event ErrorLevel="3" Project="Unity" Source="Src\Unity\Unity.csproj" Description="Converted">
</Event><Event ErrorLevel="1" Project="Unity.Configuration" Source="Src\Unity.Configuration\Unity.Configuration.csproj" Description="Your project is targeting .NET Framework 2.0 or 3.0. If your project uses assemblies requiring a newer .NET Framework, your project will fail to build. You can change the .NET Framework version by clicking Properties on the project menu and then selecting a new version in the '.NET Framework' dropdown box. (In Visual Basic, this is located on the Compile tab by clicking the 'Advanced Compiler Options...' button.)">
</Event><Event ErrorLevel="0" Project="Unity.Configuration" Source="Src\Unity.Configuration\Unity.Configuration.csproj" Description="Project converted successfully">
</Event><Event ErrorLevel="3" Project="Unity.Configuration" Source="Src\Unity.Configuration\Unity.Configuration.csproj" Description="Converted">
</Event><Event ErrorLevel="1" Project="Unity.StaticFactory" Source="Src\Unity.StaticFactory\Unity.StaticFactory.csproj" Description="Your project is targeting .NET Framework 2.0 or 3.0. If your project uses assemblies requiring a newer .NET Framework, your project will fail to build. You can change the .NET Framework version by clicking Properties on the project menu and then selecting a new version in the '.NET Framework' dropdown box. (In Visual Basic, this is located on the Compile tab by clicking the 'Advanced Compiler Options...' button.)">
</Event><Event ErrorLevel="0" Project="Unity.StaticFactory" Source="Src\Unity.StaticFactory\Unity.StaticFactory.csproj" Description="Project converted successfully">
</Event><Event ErrorLevel="3" Project="Unity.StaticFactory" Source="Src\Unity.StaticFactory\Unity.StaticFactory.csproj" Description="Converted">
</Event><Event ErrorLevel="0" Project="Tests.ObjectBuilder" Source="Tests\ObjectBuilder\Tests.ObjectBuilder.csproj" Description="Project converted successfully">
</Event><Event ErrorLevel="3" Project="Tests.ObjectBuilder" Source="Tests\ObjectBuilder\Tests.ObjectBuilder.csproj" Description="Converted">
</Event><Event ErrorLevel="0" Project="Tests.ObjectBuilder.BuildPlan" Source="Tests\ObjectBuilder.BuildPlan\Tests.ObjectBuilder.BuildPlan.csproj" Description="Project converted successfully">
</Event><Event ErrorLevel="3" Project="Tests.ObjectBuilder.BuildPlan" Source="Tests\ObjectBuilder.BuildPlan\Tests.ObjectBuilder.BuildPlan.csproj" Description="Converted">
</Event><Event ErrorLevel="0" Project="Tests.Unity" Source="Tests\Unity.Tests\Tests.Unity.csproj" Description="Project converted successfully">
</Event><Event ErrorLevel="3" Project="Tests.Unity" Source="Tests\Unity.Tests\Tests.Unity.csproj" Description="Converted">
</Event><Event ErrorLevel="0" Project="Tests.Unity.Configuration" Source="Tests\Tests.Unity.Configuration\Tests.Unity.Configuration.csproj" Description="Project converted successfully">
</Event><Event ErrorLevel="3" Project="Tests.Unity.Configuration" Source="Tests\Tests.Unity.Configuration\Tests.Unity.Configuration.csproj" Description="Converted">
</Event><Event ErrorLevel="1" Project="TestSupport.Unity" Source="Tests\TestSupport.Unity\TestSupport.Unity.csproj" Description="Your project is targeting .NET Framework 2.0 or 3.0. If your project uses assemblies requiring a newer .NET Framework, your project will fail to build. You can change the .NET Framework version by clicking Properties on the project menu and then selecting a new version in the '.NET Framework' dropdown box. (In Visual Basic, this is located on the Compile tab by clicking the 'Advanced Compiler Options...' button.)">
</Event><Event ErrorLevel="0" Project="TestSupport.Unity" Source="Tests\TestSupport.Unity\TestSupport.Unity.csproj" Description="Project converted successfully">
</Event><Event ErrorLevel="3" Project="TestSupport.Unity" Source="Tests\TestSupport.Unity\TestSupport.Unity.csproj" Description="Converted">
</Event><Event ErrorLevel="1" Project="Unity.Interception" Source="Src\Unity.Interception\Unity.Interception.csproj" Description="Your project is targeting .NET Framework 2.0 or 3.0. If your project uses assemblies requiring a newer .NET Framework, your project will fail to build. You can change the .NET Framework version by clicking Properties on the project menu and then selecting a new version in the '.NET Framework' dropdown box. (In Visual Basic, this is located on the Compile tab by clicking the 'Advanced Compiler Options...' button.)">
</Event><Event ErrorLevel="0" Project="Unity.Interception" Source="Src\Unity.Interception\Unity.Interception.csproj" Description="Project converted successfully">
</Event><Event ErrorLevel="3" Project="Unity.Interception" Source="Src\Unity.Interception\Unity.Interception.csproj" Description="Converted">
</Event><Event ErrorLevel="0" Project="Tests.Unity.Interception" Source="Tests\Tests.Unity.Interception\Tests.Unity.Interception.csproj" Description="Project converted successfully">
</Event><Event ErrorLevel="3" Project="Tests.Unity.Interception" Source="Tests\Tests.Unity.Interception\Tests.Unity.Interception.csproj" Description="Converted">
</Event><Event ErrorLevel="1" Project="Unity.Interception.Configuration" Source="Src\Unity.Interception.Configuration\Unity.Interception.Configuration.csproj" Description="Your project is targeting .NET Framework 2.0 or 3.0. If your project uses assemblies requiring a newer .NET Framework, your project will fail to build. You can change the .NET Framework version by clicking Properties on the project menu and then selecting a new version in the '.NET Framework' dropdown box. (In Visual Basic, this is located on the Compile tab by clicking the 'Advanced Compiler Options...' button.)">
</Event><Event ErrorLevel="0" Project="Unity.Interception.Configuration" Source="Src\Unity.Interception.Configuration\Unity.Interception.Configuration.csproj" Description="Project converted successfully">
</Event><Event ErrorLevel="3" Project="Unity.Interception.Configuration" Source="Src\Unity.Interception.Configuration\Unity.Interception.Configuration.csproj" Description="Converted">
</Event><Event ErrorLevel="0" Project="Tests.Unity.Interception.Configuration" Source="Tests\Tests.Unity.Interception.Configuration\Tests.Unity.Interception.Configuration.csproj" Description="Project converted successfully">
</Event><Event ErrorLevel="3" Project="Tests.Unity.Interception.Configuration" Source="Tests\Tests.Unity.Interception.Configuration\Tests.Unity.Interception.Configuration.csproj" Description="Converted">
</Event><Event ErrorLevel="0" Project="" Source="Unity.sln" Description="Solution converted successfully">
</Event><Event ErrorLevel="3" Project="" Source="Unity.sln" Description="Converted">
</Event><Event ErrorLevel="0" Project="ObjectBuilder" Source="Src\ObjectBuilder\ObjectBuilder.csproj" Description="Scan complete: Upgrade not required for project files.">
</Event><Event ErrorLevel="0" Project="Unity" Source="Src\Unity\Unity.csproj" Description="Scan complete: Upgrade not required for project files.">
</Event><Event ErrorLevel="0" Project="Unity.Configuration" Source="Src\Unity.Configuration\Unity.Configuration.csproj" Description="Scan complete: Upgrade not required for project files.">
</Event><Event ErrorLevel="0" Project="Unity.StaticFactory" Source="Src\Unity.StaticFactory\Unity.StaticFactory.csproj" Description="Scan complete: Upgrade not required for project files.">
</Event><Event ErrorLevel="0" Project="Unity.Interception" Source="Src\Unity.Interception\Unity.Interception.csproj" Description="Scan complete: Upgrade not required for project files.">
</Event><Event ErrorLevel="0" Project="Unity.Interception.Configuration" Source="Src\Unity.Interception.Configuration\Unity.Interception.Configuration.csproj" Description="Scan complete: Upgrade not required for project files.">
</Event><Event ErrorLevel="3" Project="" Source="coverage.testrunconfig" Description="Converted">
</Event><Event ErrorLevel="0" Project="" Source="coverage.testrunconfig" Description="The file was converted to the current format.">
</Event><Event ErrorLevel="3" Project="" Source="localtestrun.testrunconfig" Description="Converted">
</Event><Event ErrorLevel="0" Project="" Source="localtestrun.testrunconfig" Description="The file was converted to the current format.">
</Event><Event ErrorLevel="0" Project="Tests.ObjectBuilder" Source="Tests\ObjectBuilder\Tests.ObjectBuilder.csproj" Description="Scan complete: Upgrade not required for project files.">
</Event><Event ErrorLevel="0" Project="Tests.ObjectBuilder.BuildPlan" Source="Tests\ObjectBuilder.BuildPlan\Tests.ObjectBuilder.BuildPlan.csproj" Description="Scan complete: Upgrade not required for project files.">
</Event><Event ErrorLevel="0" Project="Tests.Unity" Source="Tests\Unity.Tests\Tests.Unity.csproj" Description="Scan complete: Upgrade not required for project files.">
</Event><Event ErrorLevel="0" Project="Tests.Unity.Configuration" Source="Tests\Tests.Unity.Configuration\Tests.Unity.Configuration.csproj" Description="Scan complete: Upgrade not required for project files.">
</Event><Event ErrorLevel="0" Project="TestSupport.Unity" Source="Tests\TestSupport.Unity\TestSupport.Unity.csproj" Description="Scan complete: Upgrade not required for project files.">
</Event><Event ErrorLevel="0" Project="Tests.Unity.Interception" Source="Tests\Tests.Unity.Interception\Tests.Unity.Interception.csproj" Description="Scan complete: Upgrade not required for project files.">
</Event><Event ErrorLevel="0" Project="Tests.Unity.Interception.Configuration" Source="Tests\Tests.Unity.Interception.Configuration\Tests.Unity.Interception.Configuration.csproj" Description="Scan complete: Upgrade not required for project files.">
</Event></UpgradeLog>